pivotr/__init__.py
pivotr/__main__.py
pivotr/pivotr.py
pivotr/file/__init__.py
pivotr/file/file_funcs.py
pivotr/networking/__init__.py
pivotr/networking/networking_funcs.py
pivotr/networking/ssh_funcs.py
pivotr/nodes/__init__.py
pivotr/nodes/node_funcs.py
pivotr/nodes/nodes.py
pivotr-0.0.2.post6.dist-info/LICENSE.md
pivotr-0.0.2.post6.dist-info/METADATA
pivotr-0.0.2.post6.dist-info/WHEEL
pivotr-0.0.2.post6.dist-info/entry_points.txt
pivotr-0.0.2.post6.dist-info/top_level.txt
pivotr-0.0.2.post6.dist-info/RECORD
