Metadata-Version: 2.1
Name: pivotr
Version: 0.0.2.post6
Summary: Pivotr - a remote command execution and pivoting framework
Author-email: Maturon Miner III <maturon@protonmail.com>
License: GNU General Public License
Project-URL: Homepage, https://gitlab.com/maturon/pivotr
Keywords: ssh,tunneling,pivoting,pentest tools
Classifier: Programming Language :: Python :: 3
Classifier: Operating System :: POSIX :: Linux
Requires-Python: >=3.12
License-File: LICENSE.md
Requires-Dist: netifaces
Requires-Dist: scp
